starlords_pulumi_shared/Builder.py
starlords_pulumi_shared/ClientConfig.py
starlords_pulumi_shared/Utils.py
starlords_pulumi_shared/__init__.py
starlords_pulumi_shared/config/AzureK8sConfig.py
starlords_pulumi_shared/config/ResourceGroupConfig.py
starlords_pulumi_shared/config/ServicePrincipalConfig.py
starlords_pulumi_shared/config/__init__.py
starlords_pulumi_shared/resources/AzureServicePrincipal.py
starlords_pulumi_shared/resources/Resource.py
starlords_pulumi_shared/resources/ResourceGroup.py
starlords_pulumi_shared/resources/__init__.py
starlords_pulumi_shared-0.0.7.dist-info/METADATA
starlords_pulumi_shared-0.0.7.dist-info/WHEEL
starlords_pulumi_shared-0.0.7.dist-info/top_level.txt
starlords_pulumi_shared-0.0.7.dist-info/RECORD
