Metadata-Version: 2.1
Name: starlords_pulumi_shared
Version: 0.0.7
Summary: A small package with shared classes
Author-email: Your Name <your.email@example.com>
Classifier: Programming Language :: Python :: 3
Classifier: Operating System :: OS Independent
Requires-Python: >=3.12
Requires-Dist: multipledispatch>=0.6
Requires-Dist: pulumi<4.0.0,>=3.5.1
Requires-Dist: pulumi-azure-native<3.0.0,>=2.12.0
Requires-Dist: pulumi-azuread<6.0.0,>=5.30.0
